README.rst
setup.py
co/__init__.py
co/component.py
co/converters.py
co/difference.py
co/feature.py
co/identifiers.py
co/mutation.py
co/organism.py
co/translation.py
co.egg-info/PKG-INFO
co.egg-info/SOURCES.txt
co.egg-info/dependency_links.txt
co.egg-info/requires.txt
co.egg-info/top_level.txt