Metadata-Version: 1.1
Name: co
Version: 0.2.0
Summary: Python library for making and tracking mutated copies of DNA components
Home-page: http://co.readthedocs.org/en/latest/
Author: Lars Schoening
Author-email: lays@biosustain.dtu.dk
License: MIT
Platform: UNKNOWN
Classifier: Development Status :: 4 - Beta
Classifier: Environment :: Other Environment
Classifier: Intended Audience :: Developers
Classifier: Intended Audience :: Science/Research
Classifier: License :: OSI Approved :: MIT License
Classifier: Operating System :: OS Independent
Classifier: Programming Language :: Python
Classifier: Programming Language :: Python :: 2.7
Classifier: Programming Language :: Python :: 3
Classifier: Topic :: Scientific/Engineering :: Bio-Informatics
